{"1.8.1-1": ["Sun May 25 2025", "Jose-Luis Blanco-Claraco", "joseluisblancoc@gmail.com"], "1.8.0-2": ["Tue Apr 22 2025", "Jose-Luis Blanco-Claraco", "joseluisblancoc@gmail.com"], "1.8.0-1": ["Sat Mar 15 2025", "Jose-Luis Blanco-Claraco", "joseluisblancoc@gmail.com"], "1.7.0-1": ["Sat Feb 22 2025", "Jose-Luis Blanco-Claraco", "joseluisblancoc@gmail.com"], "1.6.1-1": ["Fri Jan 10 2025", "Jose-Luis Blanco-Claraco", "joseluisblancoc@gmail.com"], "1.6.0-1": ["Fri Jan 03 2025", "Jose-Luis Blanco-Claraco", "joseluisblancoc@gmail.com"]}